stratokit/__init__.py
stratokit/AWS/__init__.py
stratokit/AWS/auth/__init__.py
stratokit/AWS/auth/main.py
stratokit/AWS/rds/__init__.py
stratokit/AWS/rds/main.py
stratokit-0.1.1.dist-info/licenses/LICENSE
stratokit-0.1.1.dist-info/METADATA
stratokit-0.1.1.dist-info/WHEEL
stratokit-0.1.1.dist-info/top_level.txt
stratokit-0.1.1.dist-info/RECORD
