Metadata-Version: 2.4
Name: stratokit
Version: 0.1.1
Summary: DevOps at work!
License-File: LICENSE
Dynamic: license-file
Dynamic: summary
